book_name_generator/__init__.py
book_name_generator/generate.py
book_name_generator-0.0.1.dist-info/LICENSE.txt
book_name_generator-0.0.1.dist-info/METADATA
book_name_generator-0.0.1.dist-info/WHEEL
book_name_generator-0.0.1.dist-info/top_level.txt
book_name_generator-0.0.1.dist-info/RECORD
